MANIFEST.in
README
setup.py
medved/__init__.py
medved/controller.py
medved/frozen.py
medved/model.py
medved/widgets.py
medved/wmedeval.py
medved.egg-info/PKG-INFO
medved.egg-info/SOURCES.txt
medved.egg-info/dependency_links.txt
medved.egg-info/entry_points.txt
medved.egg-info/requires.txt
medved.egg-info/top_level.txt
medved/ui/__init__.py
medved/ui/resources_rc.py
medved/ui/ui_wabout.py
medved/ui/ui_wmedeval.py