Metadata-Version: 1.1
Name: medved
Version: 2017.11.20.1
Summary: Modulation Enhanced Diffraction Viewer and EDitor
Home-page: https://soft.snbl.eu/medved.html
Author: Vadim Dyadkin
Author-email: diadkin@esrf.fr
License: GPLv3
Platform: UNKNOWN
Classifier: License :: OSI Approved :: GNU General Public License v3 (GPLv3)
Classifier: Programming Language :: Python
Classifier: Programming Language :: Python :: 3.6
Classifier: Programming Language :: Python :: Implementation :: CPython
